Metadata-Version: 2.1
Name: pokersolverquery.py
Version: 1.0.5
Summary: A Poker BaseSolver Query package for interacting with UPI engines such as PioSOLVER and jesolver
Home-page: https://github.com/mitchr1598/pokersolverquery
Author: mitchr1598
License: MIT
Platform: UNKNOWN
Classifier: License :: OSI Approved :: MIT License
Requires-Python: >=3.9.0
License-File: LICENSE
